LICENSE
uttlv/__init__.py
uttlv/encoder.py
uttlv/tlv.py
uttlv-0.7.0.dist-info/LICENSE
uttlv-0.7.0.dist-info/WHEEL
uttlv-0.7.0.dist-info/METADATA
uttlv-0.7.0.dist-info/RECORD
