Metadata-Version: 2.1
Name: uttlv
Version: 0.7.0
Summary: Python Library for TLV objects
Home-page: https://github.com/ustropo/uttlv
License: MIT
Keywords: tlv
Author: Fernando Cleber de Souza
Author-email: cleberdsouza@gmail.com
Requires-Python: >=3.7,<4.0
Classifier: Development Status :: 4 - Beta
Classifier: Intended Audience :: Developers
Classifier: License :: OSI Approved :: MIT License
Classifier: Operating System :: OS Independent
Classifier: Programming Language :: Python :: 3
Classifier: Programming Language :: Python :: 3.10
Classifier: Programming Language :: Python :: 3.7
Classifier: Programming Language :: Python :: 3.8
Classifier: Programming Language :: Python :: 3.9
Classifier: Topic :: Software Development
Project-URL: Repository, https://github.com/ustropo/uttlv
